rekcurd_airflow/__init__.py
rekcurd_airflow/_project.py
rekcurd_airflow/_version.py
rekcurd_airflow/operators/__init__.py
rekcurd_airflow/operators/evaluation_upload_operator.py
rekcurd_airflow/operators/model_delete_operator.py
rekcurd_airflow/operators/model_evaluate_operator.py
rekcurd_airflow/operators/model_switch_operator.py
rekcurd_airflow/operators/model_upload_operator.py
rekcurd_airflow/operators/rekcurd_operator.py
rekcurd_airflow-0.1.0.dist-info/LICENSE
rekcurd_airflow-0.1.0.dist-info/METADATA
rekcurd_airflow-0.1.0.dist-info/WHEEL
rekcurd_airflow-0.1.0.dist-info/top_level.txt
rekcurd_airflow-0.1.0.dist-info/RECORD
