Metadata-Version: 2.1
Name: rekcurd-airflow
Version: 0.1.0
Summary: Airflow plugins for Rekcurd
Home-page: https://github.com/rekcurd/airflow-plugin
Author: Rekcurd
Author-email: UNKNOWN
License: Apache License Version 2.0
Keywords: airflow,rekcurd
Platform: UNKNOWN
Classifier: Development Status :: 3 - Alpha
Classifier: Environment :: Web Environment
Classifier: Topic :: Software Development :: Libraries :: Application Frameworks
Classifier: Intended Audience :: Developers
Classifier: Intended Audience :: Information Technology
Classifier: License :: OSI Approved :: Apache Software License
Classifier: Operating System :: OS Independent
Classifier: Programming Language :: Python
Classifier: Programming Language :: Python :: 3
Classifier: Programming Language :: Python :: 3.6
Requires-Dist: apache-airflow (>=1.10.0)
Requires-Dist: cryptography
